exiftool_mcp/__init__.py
exiftool_mcp/server.py
exiftool_mcp-0.1.6.dist-info/licenses/LICENSE
exiftool_mcp-0.1.6.dist-info/METADATA
exiftool_mcp-0.1.6.dist-info/WHEEL
exiftool_mcp-0.1.6.dist-info/entry_points.txt
exiftool_mcp-0.1.6.dist-info/top_level.txt
exiftool_mcp-0.1.6.dist-info/RECORD
