Metadata-Version: 2.4
Name: exiftool-mcp
Version: 0.1.6
Summary: MCP server for reading metadata from files using ExifTool
License: MIT
Project-URL: Homepage, https://github.com/joshmsimpson/exiftool_mcp
Project-URL: Repository, https://github.com/joshmsimpson/exiftool_mcp
Keywords: mcp,model-context-protocol,exiftool,metadata,exif
Classifier: Development Status :: 4 - Beta
Classifier: Intended Audience :: Developers
Classifier: License :: OSI Approved :: MIT License
Classifier: Programming Language :: Python :: 3
Classifier: Programming Language :: Python :: 3.10
Classifier: Programming Language :: Python :: 3.11
Classifier: Programming Language :: Python :: 3.12
Requires-Python: >=3.10
License-File: LICENSE
Requires-Dist: mcp>=1.15.0
Dynamic: license-file
